{
  "Header": {
    "title": "New Gen Baby",
    "paragraph": "Lorem ipsum dolor sit amet, consectetur adipiscing elit. Duis sed dapibus leo nec ornare diam sed commodo nibh ante facilisis bibendum."
  },
  "About": {
    "paragraph": "팀 설명",
    "Why": [
      "이유 1",
      "이유 2",
      "이유 3",
      "이유 4"
    ]
  },
  "Gallery": [
    {
      "title": "Hoodie",
      "largeImage": "img/portfolio/hoodie1.jpg",
      "smallImage": "img/portfolio/hoodie1.jpg"
    },
    {
      "title": "Hoodie",
      "largeImage": "img/portfolio/hoodie1.jpg",
      "smallImage": "img/portfolio/hoodie1.jpg"
    },
    {
      "title": "Hoodie",
      "largeImage": "img/portfolio/hoodie1.jpg",
      "smallImage": "img/portfolio/hoodie1.jpg"
    },
    {
      "title": "Hoodie",
      "largeImage": "img/portfolio/hoodie1.jpg",
      "smallImage": "img/portfolio/hoodie1.jpg"
    },
    {
      "title": "Hoodie",
      "largeImage": "img/portfolio/hoodie1.jpg",
      "smallImage": "img/portfolio/hoodie1.jpg"
    },
    {
      "title": "Hoodie",
      "largeImage": "img/portfolio/hoodie1.jpg",
      "smallImage": "img/portfolio/hoodie1.jpg"
    }
  ],
  "Services": [
    {
      "icon": "fa fa-cart-arrow-down",
      "name": "Consectetur adipiscing",
      "text": "Lorem ipsum dolor sit amet, consectetur adipiscing elit. Duis sed dapibus leo nec ornare diam sedasd commodo nibh ante facilisis bibendum dolor feugiat at."
    },
    {
      "icon": "fa fa-plane",
      "name": "Lorem ipsum dolor",
      "text": "Lorem ipsum dolor sit amet, consectetur adipiscing elit. Duis sed dapibus leo nec ornare diam sedasd commodo nibh ante facilisis bibendum dolor feugiat at."
    },
    {
      "icon": "fa fa-pie-chart",
      "name": "Consectetur adipiscing",
      "text": "Lorem ipsum dolor sit amet, consectetur adipiscing elit. Duis sed dapibus leo nec ornare diam sedasd commodo nibh ante facilisis bibendum dolor feugiat at."
    }
  ],
  "Team": [
    {
      "img": "img/team/01.jpg",
      "name": "Yeaeun Yoon",
      "job": "Fashion Director"
    },
    {
      "img": "img/team/02.jpg",
      "name": "Sungjae Hwang",
      "job": "Managing Director"
    }
  ],
  "Contact": {
    "address": "주소",
    "phone": "+82 10 3971 4827",
    "email": "mail.newgenbaby@gmail.com",
    "instagram": "instagram.com",
    "youtube": "youtube.com",
    "naver": "naver.com"
  }
}
